leafy/data_structure.cpython-310-x86_64-linux-gnu.so
leafy/graph.cpython-310-x86_64-linux-gnu.so
leafy/digraph.cpython-310-x86_64-linux-gnu.so
leafy/__init__.py
leafy/search.cpython-310-x86_64-linux-gnu.so
leafy/shortest_path.cpython-310-x86_64-linux-gnu.so
leafy-1.0.0.dist-info/LICENSE
leafy-1.0.0.dist-info/top_level.txt
leafy-1.0.0.dist-info/WHEEL
leafy-1.0.0.dist-info/RECORD
leafy-1.0.0.dist-info/METADATA
