Metadata-Version: 2.1
Name: leafy
Version: 1.0.0
Summary: Another fast graph algorithms library
Home-page: https://github.com/ajaaliconsulting/leafy
Author: Ahmed Ali
Author-email: ahmed@ajaali.com
License: MIT
Keywords: graph dag algorithm library
Classifier: Development Status :: 5 - Production/Stable
Classifier: Intended Audience :: Developers
Classifier: License :: OSI Approved :: MIT License
Classifier: Operating System :: OS Independent
Classifier: Programming Language :: Cython
Classifier: Programming Language :: Python :: 3.7
Classifier: Programming Language :: Python :: 3.8
Classifier: Programming Language :: Python :: 3.9
Classifier: Programming Language :: Python :: 3.10
Classifier: Programming Language :: Python :: 3.11
Classifier: Topic :: Scientific/Engineering :: Mathematics
Classifier: Topic :: Software Development :: Libraries
Requires-Python: >=3.7
License-File: LICENSE
